{
  "games": [
    {
      "name": "پینگ پنگ",
      "name_en": "Ping Pong",
      "image": "ping_pong.webp",
      "route": "scores",
      "id": "b295"
    },
    {
      "name": "نبرد مزرعه",
      "name_en": "Farm Battle",
      "image": "farm_war.png",
      "route": "scores",
      "id": "ed02"
    },
    {
      "name": "ماز سرعتی",
      "name_en": "Speed Maze",
      "image": "maze.png",
      "route": "scores",
      "id": "5eeb"
    },
    {
      "name": "سوالات سرعتی و عمومی",
      "name_en": "Speed & General Questions",
      "image": "question.avif",
      "route": "quiz",
      "id": "a280"
    }
  ],
  "posts": [
    {
      "id": "1",
      "title": "json-server",
      "author": "typicode"
    }
  ],
  "comments": [
    {
      "id": "1",
      "body": "some comment",
      "postId": 1
    }
  ],
  "users": [
    {
      "id": "1c81",
      "name": "مهدی قدسی",
      "grade": "یک",
      "phone": "09378081940",
      "games": []
    },
    {
      "id": "a658",
      "name": "حسنا قدسی",
      "grade": "یک",
      "phone": "09378081940",
      "games": []
    },
    {
      "id": "d917",
      "name": "رضا غلامی ",
      "grade": "یک",
      "phone": "09114433179",
      "games": []
    },
    {
      "id": "e64c",
      "name": "فاطمه عبد... زاده",
      "grade": "سه",
      "phone": "۰۹۱۱۸۹۹۲۶۱۵",
      "games": []
    }
  ],
  "scores": [
    {
      "id": "1fba",
      "user_id": "d917",
      "game_name": "Speed & General Questions",
      "score": 240
    },
    {
      "id": "6998",
      "user_id": "d917",
      "game_name": "Farm Battle",
      "score": 123
    },
    {
      "id": "d7d0",
      "user_id": "a658",
      "game_name": "Speed & General Questions",
      "score": 200
    },
    {
      "id": "3bc0",
      "user_id": "e64c",
      "game_name": "Speed & General Questions",
      "score": 200
    }
  ]
}